frametimer/__init__.py
frametimer/frametimer.py
frametimer-2.0.0.dist-info/licenses/LICENSE
frametimer-2.0.0.dist-info/METADATA
frametimer-2.0.0.dist-info/WHEEL
frametimer-2.0.0.dist-info/top_level.txt
frametimer-2.0.0.dist-info/RECORD
