Metadata-Version: 2.4
Name: frametimer
Version: 2.0.0
Summary: An accurate clock/timer for obtaining constant framerates (FPS)
Author-email: "Orhan \"aib\" Kavrakoglu" <aibok42@gmail.com>
License: MIT
Project-URL: Homepage, https://github.com/aib/frametimer
Keywords: clock,timer,framerate,fps
Classifier: Intended Audience :: Developers
Classifier: Programming Language :: Python :: 3
Classifier: License :: OSI Approved :: MIT License
Classifier: Operating System :: OS Independent
Requires-Python: >=3.3
License-File: LICENSE
Dynamic: license-file
